source/python/CliMarkdown/__init__.py
source/python/CliMarkdown/cli_markdown.py
source/python/CliMarkdown/setup.py
pymdview-0.1.0.dist-info/METADATA
pymdview-0.1.0.dist-info/WHEEL
pymdview-0.1.0.dist-info/entry_points.txt
pymdview-0.1.0.dist-info/top_level.txt
pymdview-0.1.0.dist-info/RECORD
