Metadata-Version: 2.4
Name: PyMDView
Version: 0.1.0
Summary: A command line tool to display Markdown files
Author: CLI Markdown Team
Author-email: Matt Lowe <matt.lowe@amg-group.co.uk>
Maintainer-email: AMG Group <matt.lowe@amg-group.co.uk>
License: MIT
Project-URL: Homepage, https://github.com/AMGGroupPublic/MDView
Project-URL: Bug Tracker, https://github.com/AMGGroupPublic/MDView/issues
Classifier: Development Status :: 3 - Alpha
Classifier: Environment :: Console
Classifier: Intended Audience :: Developers
Classifier: Intended Audience :: End Users/Desktop
Classifier: License :: OSI Approved :: MIT License
Classifier: Operating System :: OS Independent
Classifier: Programming Language :: Python :: 3
Classifier: Programming Language :: Python :: 3.6
Classifier: Programming Language :: Python :: 3.7
Classifier: Programming Language :: Python :: 3.8
Classifier: Programming Language :: Python :: 3.9
Classifier: Topic :: Text Processing :: Markup
Classifier: Topic :: Utilities
Requires-Python: >=3.6
Requires-Dist: rich>=10.0.0
Requires-Dist: markdown-it-py>=2.0.0
Dynamic: author
Dynamic: requires-python
